cbpbu/__init__.py
cbpbu-0.0.1.dist-info/LICENCE.txt
cbpbu-0.0.1.dist-info/METADATA
cbpbu-0.0.1.dist-info/WHEEL
cbpbu-0.0.1.dist-info/top_level.txt
cbpbu-0.0.1.dist-info/RECORD
