Metadata-Version: 2.1
Name: cbpbu
Version: 0.0.1
Summary: This package is open for student, any student and teacher can use this.
Home-page: UNKNOWN
Author: Dipkumar
Author-email: iot.nbu@gmail.com
License: UNKNOWN
Keywords: cbpbu
Platform: UNKNOWN
Classifier: Programming Language :: Python :: 3.7
Classifier: Operating System :: OS Independent
License-File: LICENCE.txt
